//! ljumptab.rs - Opcode jump table for Lua VM (Rust translation of ljumptab.h)

/// Enum representing Lua opcodes (add more as needed)
#[derive(Debug, Clone, Copy, PartialEq, Eq)]
pub enum OpCode {
    Move,
    LoadK,
    LoadBool,
    LoadNil,
    GetUpval,
    LoadGlobal,
    SetGlobal,
    Call,
    Return,
    Add,
    Sub,
    Mul,
    Div,
    Mod,
    Pow,
    Concat,
    Jmp,
    Eq,
    Lt,
    Le,
    // ... add more as needed ...
    Unknown,
}

/// Type alias for opcode handler function
pub type OpHandler = fn(&mut crate::lua_State);

/// Example opcode handler stubs
fn op_move(_L: &mut crate::lua_State) {
    // Implement MOVE opcode logic
}
fn op_loadk(_L: &mut crate::lua_State) {
    // Implement LOADK opcode logic
}
fn op_loadbool(_L: &mut crate::lua_State) {
    // Implement LOADBOOL opcode logic
}
fn op_loadnil(_L: &mut crate::lua_State) {
    // Implement LOADNIL opcode logic
}
fn op_getupval(_L: &mut crate::lua_State) {
    // Implement GETUPVAL opcode logic
}
fn op_loadglobal(_L: &mut crate::lua_State) {
    // Implement LOADGLOBAL opcode logic
}
fn op_setglobal(_L: &mut crate::lua_State) {
    // Implement SETGLOBAL opcode logic
}
fn op_call(_L: &mut crate::lua_State) {
    // Implement CALL opcode logic
}
fn op_return(_L: &mut crate::lua_State) {
    // Implement RETURN opcode logic
}
fn op_add(_L: &mut crate::lua_State) {
    // Implement ADD opcode logic
}
fn op_sub(_L: &mut crate::lua_State) {
    // Implement SUB opcode logic
}
fn op_mul(_L: &mut crate::lua_State) {
    // Implement MUL opcode logic
}
fn op_div(_L: &mut crate::lua_State) {
    // Implement DIV opcode logic
}
fn op_mod(_L: &mut crate::lua_State) {
    // Implement MOD opcode logic
}
fn op_pow(_L: &mut crate::lua_State) {
    // Implement POW opcode logic
}
fn op_concat(_L: &mut crate::lua_State) {
    // Implement CONCAT opcode logic
}
fn op_jmp(_L: &mut crate::lua_State) {
    // Implement JMP opcode logic
}
fn op_eq(_L: &mut crate::lua_State) {
    // Implement EQ opcode logic
}
fn op_lt(_L: &mut crate::lua_State) {
    // Implement LT opcode logic
}
fn op_le(_L: &mut crate::lua_State) {
    // Implement LE opcode logic
}
fn op_unknown(_L: &mut crate::lua_State) {
    // Handle unknown opcode
}

// Macro to help define the jump table and keep it in sync with OpCode enum
macro_rules! define_opcode_jump_table {
    ( $( $handler:expr ),* $(,)? ) => {
        pub const OPCODE_JUMPTABLE: [OpHandler; count_idents!($($handler),*)] = [ $($handler),* ];
    };
}

// Helper macro to count the number of handlers
macro_rules! count_idents {
    () => {0};
    ($head:expr $(, $tail:expr)*) => {1 + count_idents!($($tail),*)};
}

// Update the jump table to match the number of opcodes
define_opcode_jump_table! {
    op_move,      // OpCode::Move
    op_loadk,     // OpCode::LoadK
    op_loadbool,  // OpCode::LoadBool
    op_loadnil,   // OpCode::LoadNil
    op_getupval,  // OpCode::GetUpval
    op_loadglobal,// OpCode::LoadGlobal
    op_setglobal, // OpCode::SetGlobal
    op_call,      // OpCode::Call
    op_return,    // OpCode::Return
    op_add,       // OpCode::Add
    op_sub,       // OpCode::Sub
    op_mul,       // OpCode::Mul
    op_div,       // OpCode::Div
    op_mod,       // OpCode::Mod
    op_pow,       // OpCode::Pow
    op_concat,    // OpCode::Concat
    op_jmp,       // OpCode::Jmp
    op_eq,        // OpCode::Eq
    op_lt,        // OpCode::Lt
    op_le,        // OpCode::Le
    // ... add more handlers in order ...
    op_unknown,   // OpCode::Unknown
}

/// Get the handler for a given opcode
pub fn get_opcode_handler(op: OpCode) -> OpHandler {
    let idx = op as usize;
    if idx < OPCODE_JUMPTABLE.len() {
        OPCODE_JUMPTABLE[idx]
    } else {
        op_unknown
    }
}

// Usage example (in your VM loop):
// let handler = get_opcode_handler(current_opcode);
// handler(lua_state);

#[cfg(test)]
mod tests {
    use super::*;
    struct DummyState;
    impl DummyState {
        fn new() -> Self { DummyState }
    }
    #[test]
    fn test_opcode_handlers() {
        let mut state = DummyState::new();
        let opcodes = [OpCode::Move, OpCode::LoadK, OpCode::LoadBool, OpCode::LoadNil, OpCode::GetUpval, OpCode::LoadGlobal, OpCode::SetGlobal, OpCode::Call, OpCode::Return, OpCode::Add, OpCode::Sub, OpCode::Mul, OpCode::Div, OpCode::Mod, OpCode::Pow, OpCode::Concat, OpCode::Jmp, OpCode::Eq, OpCode::Lt, OpCode::Le, OpCode::Unknown];
        for &op in &opcodes {
            let handler = get_opcode_handler(op);
            // Just check that the handler is callable
            // (In real tests, use a real lua_State and check effects)
            let _ = handler as usize;
        }
    }
}
